quickpath_airflow_operator/QuickpathPlatformAPIHook.py
quickpath_airflow_operator/QuickpathPlatformOperator.py
quickpath_airflow_operator/QuickpathPlatformServiceHook.py
quickpath_airflow_operator/__init__.py
quickpath_airflow_operator-1.0.2.dist-info/LICENSE.txt
quickpath_airflow_operator-1.0.2.dist-info/METADATA
quickpath_airflow_operator-1.0.2.dist-info/WHEEL
quickpath_airflow_operator-1.0.2.dist-info/top_level.txt
quickpath_airflow_operator-1.0.2.dist-info/RECORD
